Metadata-Version: 1.1
Name: mawaqit-times-calculator
Version: 0.0.3
Summary: Mawaqit Times Calculator
Home-page: https://github.com/yac69/mawaqit_times_calculator
Author: Yacine Zitouni
Author-email: iyac15@gmail.com
License: MIT
Download-URL: https://github.com/yac69/mawaqit_times_calculator/archive/refs/tags/0.0.3.tar.gz
Platform: UNKNOWN
